exegol-5.1.7.dist-info/METADATA
exegol-5.1.7.dist-info/WHEEL
exegol-5.1.7.dist-info/entry_points.txt
exegol-5.1.7.dist-info/licenses/LICENSE.md
exegol/__init__.py
exegol/__main__.py
exegol/config/ConstantConfig.py
exegol/config/DataCache.py
exegol/config/EnvInfo.py
exegol/config/UserConfig.py
exegol/config/__init__.py
exegol/console/ConsoleFormat.py
exegol/console/ExegolProgress.py
exegol/console/ExegolPrompt.py
exegol/console/ExegolStatus.py
exegol/console/LayerTextColumn.py
exegol/console/MetaGitProgress.py
exegol/console/TUI.py
exegol/console/__init__.py
exegol/console/cli/ExegolCompleter.py
exegol/console/cli/ParametersManager.py
exegol/console/cli/SyntaxFormat.py
exegol/console/cli/__init__.py
exegol/console/cli/actions/Command.py
exegol/console/cli/actions/ExegolParameters.py
exegol/console/cli/actions/GenericParameters.py
exegol/console/cli/actions/__init__.py
exegol/exceptions/ExegolExceptions.py
exegol/exceptions/__init__.py
exegol/manager/ExegolController.py
exegol/manager/ExegolManager.py
exegol/manager/LicenseManager.py
exegol/manager/TaskManager.py
exegol/manager/UpdateManager.py
exegol/manager/__init__.py
exegol/model/CacheModels.py
exegol/model/ContainerConfig.py
exegol/model/ExegolContainer.py
exegol/model/ExegolContainerTemplate.py
exegol/model/ExegolImage.py
exegol/model/ExegolModules.py
exegol/model/ExegolNetwork.py
exegol/model/LicensesTypes.py
exegol/model/MetaImages.py
exegol/model/SelectableInterface.py
exegol/model/SupabaseModels.py
exegol/model/__init__.py
exegol/utils/ContainerLogStream.py
exegol/utils/DataFileUtils.py
exegol/utils/DockerUtils.py
exegol/utils/ExeLog.py
exegol/utils/FsUtils.py
exegol/utils/GitUtils.py
exegol/utils/GuiUtils.py
exegol/utils/KeyHandler.py
exegol/utils/LocalDatastore.py
exegol/utils/MUID.py
exegol/utils/MetaSingleton.py
exegol/utils/NetworkUtils.py
exegol/utils/SessionHandler.py
exegol/utils/SupabaseUtils.py
exegol/utils/WebRegistryUtils.py
exegol/utils/__init__.py
exegol/utils/argParse.py
exegol/utils/docs/eula.md
exegol/utils/imgsync/ImageScriptSync.py
exegol/utils/imgsync/__init__.py
exegol/utils/imgsync/entrypoint.sh
exegol/utils/imgsync/spawn.sh
exegol-5.1.7.dist-info/RECORD
