Metadata-Version: 2.1
Name: Exegol
Version: 5.1.7
Summary: Python wrapper to use Exegol, a container based fully featured and community-driven hacking environment.
Keywords: pentest,redteam,ctf,exegol
Author-Email: Dramelac <dramelac@pm.me>, Shutdown <nwodtuhs@pm.me>
License: # Exegol Software License (ESL) - Version 1.0
Classifier: Development Status :: 5 - Production/Stable
Classifier: Programming Language :: Python :: 3.9
Classifier: Programming Language :: Python :: 3.10
Classifier: Programming Language :: Python :: 3.11
Classifier: Programming Language :: Python :: 3.12
Classifier: Programming Language :: Python :: 3.13
Classifier: License :: OSI Approved :: GNU General Public License v3 (GPLv3)
Classifier: Operating System :: OS Independent
Project-URL: Homepage, https://exegol.readthedocs.io/
Project-URL: Documentation, https://exegol.readthedocs.io/
Project-URL: Repository, https://github.com/ThePorgs/Exegol
Project-URL: Issues, https://github.com/ThePorgs/Exegol/issues
Project-URL: Funding, https://patreon.com/nwodtuhs
Requires-Python: >=3.9.2
Requires-Dist: docker~=7.1.0
Requires-Dist: requests~=2.32.5
Requires-Dist: rich~=14.2.0
Requires-Dist: GitPython~=3.1.43
Requires-Dist: PyYAML>=6.0.3
Requires-Dist: argcomplete~=3.6.3
Requires-Dist: tzlocal~=5.2; platform_system != "Linux"
Requires-Dist: ifaddr~=0.2.0
Requires-Dist: supabase~=2.24.0
Requires-Dist: pydantic~=2.12.4
Requires-Dist: pyjwt>=2.10.1
Requires-Dist: pyjwt[crypto]>=2.10.1
Requires-Dist: cryptography~=46.0.3
Requires-Dist: python-dateutil>=2.9.0; python_version < "3.11"
